

[
{"symptoms":"Diseases of Abdomen"},
{"symptoms":"Digestive Impairment"},
{"symptoms":"Retention of Urine"},
{"symptoms":"Fever"},
{"symptoms":"Anaemia"},
{"symptoms":"Urinary Disorders"},
{"symptoms":"Tastlessness"},
{"symptoms":"Malabsorption Syndrome"},
{"symptoms":"Obesity"},
{"symptoms":"Loss of Immunity"},
{"symptoms":"Pediatric Conditions"},
{"symptoms":"Haemorrhoids"},
{"symptoms":"Excessive Urine Flow"},
{"symptoms":"Vaginal Pain"},
{"symptoms":"Epilepsy"},
{"symptoms":"Diarrhoea"},
{"symptoms":"Gastro Enteritis"},
{"symptoms":"Dysentery"},
{"symptoms":"Helminthiasis"},
{"symptoms":"Cough"},
{"symptoms":"Asthma"},
{"symptoms":"Tuberculosis"},
{"symptoms":"Kapha Dosa"},
{"symptoms":"Ulcer"},
{"symptoms":"Dysuria"},
{"symptoms":"Calculus"},
{"symptoms":"Cyst"},
{"symptoms":"Heart Disease"},
{"symptoms":"Loss of Strength"},
{"symptoms":"Tastelessness"},
{"symptoms":"Taeniasis"},
{"symptoms":"Laxative"},
{"symptoms":"Diseases of Throat"},
{"symptoms":"Abdominal Lump"},
{"symptoms":"Liver Disorder"},
{"symptoms":"Spleen Disorder"},
{"symptoms":"Weakness"},
{"symptoms":"Skin Diseases"},
{"symptoms":"Vitiligo"},
{"symptoms":"Disorder of Blood"},
{"symptoms":"Hiccups"},
{"symptoms":"Eye Disease"},
{"symptoms":"Head Disease"},
{"symptoms":"Disease of Skin"},
{"symptoms":"Throat Disease"},
{"symptoms":"Leucoderma"},
{"symptoms":"Uterus Disorder"},
{"symptoms":"Aplenic Disease"},
{"symptoms":"Itching"},
{"symptoms":"Stomach"},
{"symptoms":"Body Strength"},
{"symptoms":"Disorders of blood"},
{"symptoms":"Acute Alcoholism"},
{"symptoms":"Intoxication"},
{"symptoms":"Alcoholic Intoxication"},
{"symptoms":"Semen Vitiation"},
{"symptoms":"Mental Disorder"},
{"symptoms":"Incoherent Speech"},
{"symptoms":"Decrease in Memory"},
{"symptoms":"Menstrual Disorder"},
{"symptoms":"Digestive Fire"},
{"symptoms":"Wrinkles"},
{"symptoms":"Stiffness in Thigh Muscles"},
{"symptoms":"Lock Jaw"},
{"symptoms":"Intoxication"},
{"symptoms":"Hiccup"},
{"symptoms":"Hoarseness of Voice"},
{"symptoms":"Slow Poison"},
{"symptoms":"Nausea"},
{"symptoms":"Vomiting"},
{"symptoms":"Wound"},
{"symptoms":"Infertility"},
{"symptoms":"Obstruction in Urinary Tract"},
{"symptoms":"Diabetes"},
{"symptoms":"Nutrition to Body"},
{"symptoms":"Fatigue"},
{"symptoms":"Mental Weakness"},
{"symptoms":"Impairment of Memory"},
{"symptoms":"Piles"},
{"symptoms":"Burning Sensation"},
{"symptoms":"Pin in the lower back"},
{"symptoms":"Headache"},
{"symptoms":"Pin in Urinary Bladder"},
{"symptoms":"Body Ache"},
{"symptoms":"Shortness of Breathe"},
{"symptoms":"Cardiac Failure"},
{"symptoms":"Pain in Arm"},
{"symptoms":"Bone Marrow Disorder"}

]